{
  "title": "Worm",
  "info": "Snake game",
  "icon": [
    ["\\151", "\\131", "\\131", "\\131", "\\131", "\\148"],
    ["\\149", "\\132", " ", " ", " ", "\\149"],
    ["\\149", "\\141", "\\140", "\\135", "\\144", "\\149"],
    ["\\138", "\\143", "\\143", "\\143", "\\143", "\\133"]
  ],
  "icon_bg_color": [
    ["k", "k", "k", "k", "k", "y"],
    ["k", "k", "k", "k", "k", "y"],
    ["k", "k", "k", "k", "k", "y"],
    ["y", "y", "y", "y", "y", "y"]
  ],
  "icon_fg_color": [
    ["y", "y", "y", "y", "y", "k"],
    ["y", "r", "y", "y", "y", "k"],
    ["y", "g", "g", "g", "r", "k"],
    ["k", "k", "k", "k", "k", "k"]
  ]
}
